jss_optimizer/__init__.py
jss_optimizer/jss_optimizer.py
jss_optimizer-0.1.2.dist-info/METADATA
jss_optimizer-0.1.2.dist-info/WHEEL
jss_optimizer-0.1.2.dist-info/top_level.txt
jss_optimizer-0.1.2.dist-info/RECORD
