Metadata-Version: 2.1
Name: jss-optimizer
Version: 0.1.2
Author: Jegadit S Saravanan
Author-email: jegaditssaravanan@yahoo.com
Keywords: machine-learning,parameter optimization,genetic algorithm,simulated annealing
Classifier: Programming Language :: Python :: 3
Classifier: Operating System :: OS Independent
Classifier: Intended Audience :: Developers
Classifier: Topic :: Scientific/Engineering :: Artificial Intelligence
Requires-Dist: numpy
Requires-Dist: tqdm
